{
    "objects": [
        {
            "attributes": {
                "description": "",
                "kibanaSavedObjectMeta": {
                    "searchSourceJSON": "{\"filter\": []}"
                },
                "savedSearchId": "Syslog-system-logs-ecs",
                "title": "Syslog events by hostname [Filebeat System] ECS",
                "uiStateJSON": "{}",
                "version": 1,
                "visState": "{\"type\": \"histogram\", \"listeners\": {}, \"title\": \"Syslog events by hostname ECS\", \"params\": {\"defaultYExtents\": false, \"addTooltip\": true, \"shareYAxis\": true, \"addLegend\": true, \"addTimeMarker\": false, \"mode\": \"stacked\", \"scale\": \"linear\", \"times\": [], \"legendPosition\": \"right\", \"yAxis\": {}, \"setYExtents\": false}, \"aggs\": [{\"enabled\": true, \"schema\": \"metric\", \"id\": \"1\", \"params\": {}, \"type\": \"count\"}, {\"enabled\": true, \"schema\": \"segment\", \"id\": \"2\", \"params\": {\"interval\": \"auto\", \"field\": \"@timestamp\", \"min_doc_count\": 1, \"customInterval\": \"2h\", \"extended_bounds\": {}}, \"type\": \"date_histogram\"}, {\"enabled\": true, \"schema\": \"group\", \"id\": \"3\", \"params\": {\"order\": \"desc\", \"field\": \"host.hostname\", \"size\": 5, \"orderBy\": \"1\"}, \"type\": \"terms\"}]}"
            },
            "id": "Syslog-events-by-hostname-ecs",
            "type": "visualization",
            "version": 2
        },
        {
            "attributes": {
                "description": "",
                "kibanaSavedObjectMeta": {
                    "searchSourceJSON": "{\"filter\": []}"
                },
                "savedSearchId": "Syslog-system-logs-ecs",
                "title": "Syslog hostnames and processes [Filebeat System] ECS",
                "uiStateJSON": "{}",
                "version": 1,
                "visState": "{\"type\": \"pie\", \"listeners\": {}, \"title\": \"Syslog hostnames and processes ECS\", \"params\": {\"addTooltip\": true, \"shareYAxis\": true, \"legendPosition\": \"bottom\", \"isDonut\": true, \"addLegend\": true}, \"aggs\": [{\"enabled\": true, \"schema\": \"metric\", \"id\": \"1\", \"params\": {}, \"type\": \"count\"}, {\"enabled\": true, \"schema\": \"segment\", \"id\": \"2\", \"params\": {\"order\": \"desc\", \"field\": \"host.hostname\", \"size\": 5, \"orderBy\": \"1\"}, \"type\": \"terms\"}, {\"enabled\": true, \"schema\": \"segment\", \"id\": \"3\", \"params\": {\"order\": \"desc\", \"field\": \"process.name\", \"size\": 5, \"orderBy\": \"1\"}, \"type\": \"terms\"}]}"
            },
            "id": "Syslog-hostnames-and-processes-ecs",
            "type": "visualization",
            "version": 2
        },
        {
            "attributes": {
                "columns": [
                    "host.hostname",
                    "process.name",
                    "message"
                ],
                "description": "",
                "hits": 0,
                "kibanaSavedObjectMeta": {
                    "searchSourceJSON": "{\"filter\": [], \"highlightAll\": true, \"highlight\": {\"post_tags\": [\"@/kibana-highlighted-field@\"], \"pre_tags\": [\"@kibana-highlighted-field@\"], \"fields\": {\"*\": {}}, \"fragment_size\": 2147483647, \"require_field_match\": false}, \"query\": {\"query\": \"event.dataset:system.syslog\", \"language\": \"kuery\"}, \"index\": \"filebeat-*\"}"
                },
                "sort": [
                    "@timestamp",
                    "desc"
                ],
                "title": "Syslog logs [Filebeat System] ECS",
                "version": 1
            },
            "id": "Syslog-system-logs-ecs",
            "type": "search",
            "version": 2
        },
        {
            "attributes": {
                "description": "",
                "kibanaSavedObjectMeta": {
                    "searchSourceJSON": "{}"
                },
                "title": "Dashboards [Filebeat System] ECS",
                "uiStateJSON": "{}",
                "version": 1,
                "visState": "{\"type\": \"markdown\", \"title\": \"Dashboards [Filebeat System] ECS\", \"params\": {\"markdown\": \"[Syslog](#/dashboard/Filebeat-syslog-dashboard-ecs) | [Sudo commands](#/dashboard/277876d0-fa2c-11e6-bbd3-29c986c96e5a-ecs) | [SSH logins](#/dashboard/5517a150-f9ce-11e6-8115-a7c18106d86a-ecs) | [New users and groups](#/dashboard/0d3f2380-fa78-11e6-ae9b-81e5311e8cab-ecs)\", \"fontSize\": 12}, \"aggs\": []}"
            },
            "id": "327417e0-8462-11e7-bab8-bd2f0fb42c54-ecs",
            "type": "visualization",
            "version": 1
        },
        {
            "attributes": {
                "description": "Syslog dashboard from the Filebeat System module",
                "hits": 0,
                "kibanaSavedObjectMeta": {
                    "searchSourceJSON": "{\"filter\": [], \"version\": true, \"highlightAll\": true, \"query\": {\"query\": \"\", \"language\": \"kuery\"}}"
                },
                "optionsJSON": "{\"darkTheme\": false}",
                "panelsJSON": "[{\"id\": \"Syslog-events-by-hostname-ecs\", \"col\": 1, \"type\": \"visualization\", \"size_x\": 8, \"row\": 2, \"panelIndex\": 1, \"size_y\": 4}, {\"id\": \"Syslog-hostnames-and-processes-ecs\", \"col\": 9, \"type\": \"visualization\", \"size_x\": 4, \"row\": 2, \"panelIndex\": 2, \"size_y\": 4}, {\"sort\": [\"@timestamp\", \"desc\"], \"id\": \"Syslog-system-logs-ecs\", \"col\": 1, \"type\": \"search\", \"size_x\": 12, \"row\": 6, \"columns\": [\"host.hostname\", \"process.name\", \"message\"], \"panelIndex\": 3, \"size_y\": 7}, {\"id\": \"327417e0-8462-11e7-bab8-bd2f0fb42c54-ecs\", \"col\": 1, \"type\": \"visualization\", \"size_x\": 12, \"row\": 1, \"panelIndex\": 4, \"size_y\": 1}]",
                "timeRestore": false,
                "title": "[Filebeat System] Syslog dashboard ECS",
                "uiStateJSON": "{}",
                "version": 1
            },
            "id": "Filebeat-syslog-dashboard-ecs",
            "type": "dashboard",
            "version": 6
        }
    ],
    "version": "6.0.0-beta1-SNAPSHOT"
}